czmq/__init__.py
czmq/_czmq_ctypes.py
czmq/libczmq.so
czmq/libzmq.so
pyzyre/__init__.py
pyzyre/_version.py
pyzyre/broker.py
pyzyre/chat.py
pyzyre/constants.py
pyzyre/gateway.py
pyzyre/zcerts.py
pyzyre/zpipe.py
pyzyre/client/__init__.py
pyzyre/client/_actor_handler.py
pyzyre/client/_task.py
pyzyre/utils/__init__.py
pyzyre/utils/color.py
pyzyre/utils/znetwork.py
zyre/__init__.py
zyre/_zyre_ctypes.py
zyre/libzyre.so
pyzyre-0.0a28.dist-info/LICENSE
pyzyre-0.0a28.dist-info/METADATA
pyzyre-0.0a28.dist-info/WHEEL
pyzyre-0.0a28.dist-info/entry_points.txt
pyzyre-0.0a28.dist-info/top_level.txt
pyzyre-0.0a28.dist-info/RECORD
